whendone/__init__.py
whendone/whendone.py
whendone-1.2.0.dist-info/LICENSE
whendone-1.2.0.dist-info/WHEEL
whendone-1.2.0.dist-info/METADATA
whendone-1.2.0.dist-info/RECORD
