Metadata-Version: 2.1
Name: whendone
Version: 1.2.0
Summary: Python package to notify you when your function is done through Telegram and/or Slack!
License: MIT
Author: Sabri Barac
Requires-Python: >=3.9,<4.0
Classifier: License :: OSI Approved :: MIT License
Classifier: Programming Language :: Python :: 3
Classifier: Programming Language :: Python :: 3.9
Classifier: Programming Language :: Python :: 3.10
Classifier: Programming Language :: Python :: 3.11
Requires-Dist: requests (>=2.28.2,<3.0.0)
Requires-Dist: slack-sdk (>=3.19.5,<4.0.0)
